CK4ML/__init__.py
CK4ML/imgconv.py
CK4ML/kernels.py
CK4ML-0.0.2.dist-info/LICENSE
CK4ML-0.0.2.dist-info/METADATA
CK4ML-0.0.2.dist-info/WHEEL
CK4ML-0.0.2.dist-info/top_level.txt
CK4ML-0.0.2.dist-info/RECORD
