Metadata-Version: 2.1
Name: CK4ML
Version: 0.0.2
Summary: causal knowledge for machine learning
Home-page: https://github.com/whw199833/CK4ML
Author: harvin
Author-email: haowenw98@gmail.com
Classifier: Programming Language :: Python :: 3
Classifier: License :: OSI Approved :: MIT License
Classifier: Operating System :: OS Independent
Requires-Python: >=3.6
License-File: LICENSE
